{
  "data": {
    "__schema": {
      "queryType": {
        "name": "Query"
      },
      "mutationType": {
        "name": "Mutation"
      },
      "subscriptionType": null,
      "types": [
        {
          "kind": "OBJECT",
          "name": "Query",
          "description": "The query root of this schema. See available queries.",
          "fields": [
            {
              "name": "node",
              "description": null,
              "args": [
                {
                  "name": "id",
                  "description": null,
                  "type": {
                    "kind": "NON_NULL",
                    "name": "Non-Null",
                    "ofType": {
                      "kind": "SCALAR",
                      "name": "ID",
                      "ofType": null
                    }
                  },
                  "defaultValue": null
                }
              ],
              "type": {
                "kind": "INTERFACE",
                "name": "Node",
                "ofType": null
              },
              "isDeprecated": false,
              "deprecationReason": null
            },
            {
              "name": "root",
              "description": "Root object to get viewer related collections",
              "args": [

              ],
              "type": {
                "kind": "OBJECT",
                "name": "Viewer",
                "ofType": null
              },
              "isDeprecated": false,
              "deprecationReason": null
            }
          ],
          "inputFields": null,
          "interfaces": [

          ],
          "enumValues": null,
          "possibleTypes": null
        },
        {
          "kind": "INTERFACE",
          "name": "Node",
          "description": null,
          "fields": [
            {
              "name": "id",
              "description": null,
              "args": [

              ],
              "type": {
                "kind": "NON_NULL",
                "name": "Non-Null",
                "ofType": {
                  "kind": "SCALAR",
                  "name": "ID",
                  "ofType": null
                }
              },
              "isDeprecated": false,
              "deprecationReason": null
            }
          ],
          "inputFields": null,
          "interfaces": null,
          "enumValues": null,
          "possibleTypes": [
            {
              "kind": "OBJECT",
              "name": "Comment",
              "ofType": null
            },
            {
              "kind": "OBJECT",
              "name": "Post",
              "ofType": null
            },
            {
              "kind": "OBJECT",
              "name": "User",
              "ofType": null
            },
            {
              "kind": "OBJECT",
              "name": "Viewer",
              "ofType": null
            }
          ]
        },
        {
          "kind": "SCALAR",
          "name": "ID",
          "description": null,
          "fields": null,
          "inputFields": null,
          "interfaces": null,
          "enumValues": null,
          "possibleTypes": null
        },
        {
          "kind": "OBJECT",
          "name": "Viewer",
          "description": "Support unassociated root queries that fetches collections. Supports fetching posts and users collection",
          "fields": [
            {
              "name": "current_user",
              "description": "Returns current signed in user object",
              "args": [

              ],
              "type": {
                "kind": "OBJECT",
                "name": "User",
                "ofType": null
              },
              "isDeprecated": false,
              "deprecationReason": null
            },
            {
              "name": "id",
              "description": null,
              "args": [

              ],
              "type": {
                "kind": "NON_NULL",
                "name": "Non-Null",
                "ofType": {
                  "kind": "SCALAR",
                  "name": "ID",
                  "ofType": null
                }
              },
              "isDeprecated": false,
              "deprecationReason": null
            },
            {
              "name": "posts",
              "description": "Post connection to fetch paginated posts collection.",
              "args": [
                {
                  "name": "first",
                  "description": null,
                  "type": {
                    "kind": "SCALAR",
                    "name": "Int",
                    "ofType": null
                  },
                  "defaultValue": null
                },
                {
                  "name": "after",
                  "description": null,
                  "type": {
                    "kind": "SCALAR",
                    "name": "String",
                    "ofType": null
                  },
                  "defaultValue": null
                },
                {
                  "name": "last",
                  "description": null,
                  "type": {
                    "kind": "SCALAR",
                    "name": "Int",
                    "ofType": null
                  },
                  "defaultValue": null
                },
                {
                  "name": "before",
                  "description": null,
                  "type": {
                    "kind": "SCALAR",
                    "name": "String",
                    "ofType": null
                  },
                  "defaultValue": null
                },
                {
                  "name": "filter",
                  "description": null,
                  "type": {
                    "kind": "SCALAR",
                    "name": "String",
                    "ofType": null
                  },
                  "defaultValue": null
                },
                {
                  "name": "tag",
                  "description": null,
                  "type": {
                    "kind": "SCALAR",
                    "name": "String",
                    "ofType": null
                  },
                  "defaultValue": null
                },
                {
                  "name": "order",
                  "description": null,
                  "type": {
                    "kind": "SCALAR",
                    "name": "String",
                    "ofType": null
                  },
                  "defaultValue": "\"id\""
                }
              ],
              "type": {
                "kind": "OBJECT",
                "name": "PostConnection",
                "ofType": null
              },
              "isDeprecated": false,
              "deprecationReason": null
            },
            {
              "name": "tags",
              "description": "List of tags for the post",
              "args": [

              ],
              "type": {
                "kind": "LIST",
                "name": "List",
                "ofType": {
                  "kind": "SCALAR",
                  "name": "String",
                  "ofType": null
                }
              },
              "isDeprecated": false,
              "deprecationReason": null
            }
          ],
          "inputFields": null,
          "interfaces": [
            {
              "kind": "INTERFACE",
              "name": "Node",
              "ofType": null
            }
          ],
          "enumValues": null,
          "possibleTypes": null
        },
        {
          "kind": "OBJECT",
          "name": "PostConnection",
          "description": null,
          "fields": [
            {
              "name": "edges",
              "description": null,
              "args": [

              ],
              "type": {
                "kind": "LIST",
                "name": "List",
                "ofType": {
                  "kind": "OBJECT",
                  "name": "PostEdge",
                  "ofType": null
                }
              },
              "isDeprecated": false,
              "deprecationReason": null
            },
            {
              "name": "pageInfo",
              "description": null,
              "args": [

              ],
              "type": {
                "kind": "OBJECT",
                "name": "PageInfo",
                "ofType": null
              },
              "isDeprecated": false,
              "deprecationReason": null
            }
          ],
          "inputFields": null,
          "interfaces": [

          ],
          "enumValues": null,
          "possibleTypes": null
        },
        {
          "kind": "OBJECT",
          "name": "PostEdge",
          "description": null,
          "fields": [
            {
              "name": "cursor",
              "description": null,
              "args": [

              ],
              "type": {
                "kind": "NON_NULL",
                "name": "Non-Null",
                "ofType": {
                  "kind": "SCALAR",
                  "name": "String",
                  "ofType": null
                }
              },
              "isDeprecated": false,
              "deprecationReason": null
            },
            {
              "name": "node",
              "description": null,
              "args": [

              ],
              "type": {
                "kind": "OBJECT",
                "name": "Post",
                "ofType": null
              },
              "isDeprecated": false,
              "deprecationReason": null
            }
          ],
          "inputFields": null,
          "interfaces": [

          ],
          "enumValues": null,
          "possibleTypes": null
        },
        {
          "kind": "OBJECT",
          "name": "Post",
          "description": "A single post entry returns a post with author, total votes and comments",
          "fields": [
            {
              "name": "body",
              "description": "The body of this post",
              "args": [

              ],
              "type": {
                "kind": "SCALAR",
                "name": "String",
                "ofType": null
              },
              "isDeprecated": false,
              "deprecationReason": null
            },
            {
              "name": "comments",
              "description": "All comments association with this post. Returns comments collection and accepts arguments.",
              "args": [
                {
                  "name": "first",
                  "description": null,
                  "type": {
                    "kind": "SCALAR",
                    "name": "Int",
                    "ofType": null
                  },
                  "defaultValue": null
                },
                {
                  "name": "after",
                  "description": null,
                  "type": {
                    "kind": "SCALAR",
                    "name": "String",
                    "ofType": null
                  },
                  "defaultValue": null
                },
                {
                  "name": "last",
                  "description": null,
                  "type": {
                    "kind": "SCALAR",
                    "name": "Int",
                    "ofType": null
                  },
                  "defaultValue": null
                },
                {
                  "name": "before",
                  "description": null,
                  "type": {
                    "kind": "SCALAR",
                    "name": "String",
                    "ofType": null
                  },
                  "defaultValue": null
                },
                {
                  "name": "order",
                  "description": null,
                  "type": {
                    "kind": "SCALAR",
                    "name": "String",
                    "ofType": null
                  },
                  "defaultValue": "\"id\""
                }
              ],
              "type": {
                "kind": "OBJECT",
                "name": "CommentConnection",
                "ofType": null
              },
              "isDeprecated": false,
              "deprecationReason": null
            },
            {
              "name": "comments_count",
              "description": "The total numner of comments on this post",
              "args": [

              ],
              "type": {
                "kind": "SCALAR",
                "name": "String",
                "ofType": null
              },
              "isDeprecated": false,
              "deprecationReason": null
            },
            {
              "name": "created_at",
              "description": "The time at which this post was created",
              "args": [

              ],
              "type": {
                "kind": "SCALAR",
                "name": "String",
                "ofType": null
              },
              "isDeprecated": false,
              "deprecationReason": null
            },
            {
              "name": "excerpt",
              "description": "The short description of this post",
              "args": [

              ],
              "type": {
                "kind": "SCALAR",
                "name": "String",
                "ofType": null
              },
              "isDeprecated": false,
              "deprecationReason": null
            },
            {
              "name": "id",
              "description": null,
              "args": [

              ],
              "type": {
                "kind": "NON_NULL",
                "name": "Non-Null",
                "ofType": {
                  "kind": "SCALAR",
                  "name": "ID",
                  "ofType": null
                }
              },
              "isDeprecated": false,
              "deprecationReason": null
            },
            {
              "name": "slug",
              "description": "The slug of this post",
              "args": [

              ],
              "type": {
                "kind": "SCALAR",
                "name": "String",
                "ofType": null
              },
              "isDeprecated": false,
              "deprecationReason": null
            },
            {
              "name": "tags",
              "description": "List of tags for the post",
              "args": [

              ],
              "type": {
                "kind": "LIST",
                "name": "List",
                "ofType": {
                  "kind": "SCALAR",
                  "name": "String",
                  "ofType": null
                }
              },
              "isDeprecated": false,
              "deprecationReason": null
            },
            {
              "name": "title",
              "description": "The title of this post",
              "args": [

              ],
              "type": {
                "kind": "SCALAR",
                "name": "String",
                "ofType": null
              },
              "isDeprecated": false,
              "deprecationReason": null
            },
            {
              "name": "user",
              "description": "Owner of this post",
              "args": [

              ],
              "type": {
                "kind": "OBJECT",
                "name": "User",
                "ofType": null
              },
              "isDeprecated": false,
              "deprecationReason": null
            },
            {
              "name": "user_id",
              "description": "The id of this post author",
              "args": [

              ],
              "type": {
                "kind": "SCALAR",
                "name": "Int",
                "ofType": null
              },
              "isDeprecated": false,
              "deprecationReason": null
            },
            {
              "name": "voted",
              "description": "Is this post voted by current user?",
              "args": [

              ],
              "type": {
                "kind": "SCALAR",
                "name": "Boolean",
                "ofType": null
              },
              "isDeprecated": false,
              "deprecationReason": null
            },
            {
              "name": "votes_count",
              "description": "The total numner of votes on this post",
              "args": [

              ],
              "type": {
                "kind": "SCALAR",
                "name": "String",
                "ofType": null
              },
              "isDeprecated": false,
              "deprecationReason": null
            }
          ],
          "inputFields": null,
          "interfaces": [
            {
              "kind": "INTERFACE",
              "name": "Node",
              "ofType": null
            }
          ],
          "enumValues": null,
          "possibleTypes": null
        },
        {
          "kind": "SCALAR",
          "name": "String",
          "description": null,
          "fields": null,
          "inputFields": null,
          "interfaces": null,
          "enumValues": null,
          "possibleTypes": null
        },
        {
          "kind": "SCALAR",
          "name": "Int",
          "description": null,
          "fields": null,
          "inputFields": null,
          "interfaces": null,
          "enumValues": null,
          "possibleTypes": null
        },
        {
          "kind": "OBJECT",
          "name": "User",
          "description": "An user entry, returns basic user information",
          "fields": [
            {
              "name": "created_at",
              "description": "The date this user created an account",
              "args": [

              ],
              "type": {
                "kind": "SCALAR",
                "name": "String",
                "ofType": null
              },
              "isDeprecated": false,
              "deprecationReason": null
            },
            {
              "name": "email",
              "description": "The email of this user",
              "args": [

              ],
              "type": {
                "kind": "SCALAR",
                "name": "String",
                "ofType": null
              },
              "isDeprecated": false,
              "deprecationReason": null
            },
            {
              "name": "id",
              "description": null,
              "args": [

              ],
              "type": {
                "kind": "NON_NULL",
                "name": "Non-Null",
                "ofType": {
                  "kind": "SCALAR",
                  "name": "ID",
                  "ofType": null
                }
              },
              "isDeprecated": false,
              "deprecationReason": null
            },
            {
              "name": "name",
              "description": "The name of this user",
              "args": [

              ],
              "type": {
                "kind": "SCALAR",
                "name": "String",
                "ofType": null
              },
              "isDeprecated": false,
              "deprecationReason": null
            }
          ],
          "inputFields": null,
          "interfaces": [
            {
              "kind": "INTERFACE",
              "name": "Node",
              "ofType": null
            }
          ],
          "enumValues": null,
          "possibleTypes": null
        },
        {
          "kind": "OBJECT",
          "name": "CommentConnection",
          "description": null,
          "fields": [
            {
              "name": "edges",
              "description": null,
              "args": [

              ],
              "type": {
                "kind": "LIST",
                "name": "List",
                "ofType": {
                  "kind": "OBJECT",
                  "name": "CommentEdge",
                  "ofType": null
                }
              },
              "isDeprecated": false,
              "deprecationReason": null
            },
            {
              "name": "pageInfo",
              "description": null,
              "args": [

              ],
              "type": {
                "kind": "OBJECT",
                "name": "PageInfo",
                "ofType": null
              },
              "isDeprecated": false,
              "deprecationReason": null
            }
          ],
          "inputFields": null,
          "interfaces": [

          ],
          "enumValues": null,
          "possibleTypes": null
        },
        {
          "kind": "OBJECT",
          "name": "CommentEdge",
          "description": null,
          "fields": [
            {
              "name": "cursor",
              "description": null,
              "args": [

              ],
              "type": {
                "kind": "NON_NULL",
                "name": "Non-Null",
                "ofType": {
                  "kind": "SCALAR",
                  "name": "String",
                  "ofType": null
                }
              },
              "isDeprecated": false,
              "deprecationReason": null
            },
            {
              "name": "node",
              "description": null,
              "args": [

              ],
              "type": {
                "kind": "OBJECT",
                "name": "Comment",
                "ofType": null
              },
              "isDeprecated": false,
              "deprecationReason": null
            }
          ],
          "inputFields": null,
          "interfaces": [

          ],
          "enumValues": null,
          "possibleTypes": null
        },
        {
          "kind": "OBJECT",
          "name": "Comment",
          "description": "A single comment entry returns a comment with author and total votes",
          "fields": [
            {
              "name": "body",
              "description": "The body of this comment",
              "args": [

              ],
              "type": {
                "kind": "SCALAR",
                "name": "String",
                "ofType": null
              },
              "isDeprecated": false,
              "deprecationReason": null
            },
            {
              "name": "created_at",
              "description": "The date on which the comment was posted",
              "args": [

              ],
              "type": {
                "kind": "SCALAR",
                "name": "String",
                "ofType": null
              },
              "isDeprecated": false,
              "deprecationReason": null
            },
            {
              "name": "id",
              "description": null,
              "args": [

              ],
              "type": {
                "kind": "NON_NULL",
                "name": "Non-Null",
                "ofType": {
                  "kind": "SCALAR",
                  "name": "ID",
                  "ofType": null
                }
              },
              "isDeprecated": false,
              "deprecationReason": null
            },
            {
              "name": "is_owner",
              "description": "Is the comment belongs to current user?",
              "args": [

              ],
              "type": {
                "kind": "SCALAR",
                "name": "Boolean",
                "ofType": null
              },
              "isDeprecated": false,
              "deprecationReason": null
            },
            {
              "name": "user",
              "description": "Owner of this comment",
              "args": [

              ],
              "type": {
                "kind": "OBJECT",
                "name": "User",
                "ofType": null
              },
              "isDeprecated": false,
              "deprecationReason": null
            },
            {
              "name": "voted",
              "description": "Is this comment voted by current user?",
              "args": [

              ],
              "type": {
                "kind": "SCALAR",
                "name": "Boolean",
                "ofType": null
              },
              "isDeprecated": false,
              "deprecationReason": null
            },
            {
              "name": "votes_count",
              "description": "The total number of votes on this comment",
              "args": [

              ],
              "type": {
                "kind": "SCALAR",
                "name": "String",
                "ofType": null
              },
              "isDeprecated": false,
              "deprecationReason": null
            }
          ],
          "inputFields": null,
          "interfaces": [
            {
              "kind": "INTERFACE",
              "name": "Node",
              "ofType": null
            }
          ],
          "enumValues": null,
          "possibleTypes": null
        },
        {
          "kind": "SCALAR",
          "name": "Boolean",
          "description": null,
          "fields": null,
          "inputFields": null,
          "interfaces": null,
          "enumValues": null,
          "possibleTypes": null
        },
        {
          "kind": "OBJECT",
          "name": "PageInfo",
          "description": "Metadata about a connection",
          "fields": [
            {
              "name": "hasNextPage",
              "description": null,
              "args": [

              ],
              "type": {
                "kind": "NON_NULL",
                "name": "Non-Null",
                "ofType": {
                  "kind": "SCALAR",
                  "name": "Boolean",
                  "ofType": null
                }
              },
              "isDeprecated": false,
              "deprecationReason": null
            },
            {
              "name": "hasPreviousPage",
              "description": null,
              "args": [

              ],
              "type": {
                "kind": "NON_NULL",
                "name": "Non-Null",
                "ofType": {
                  "kind": "SCALAR",
                  "name": "Boolean",
                  "ofType": null
                }
              },
              "isDeprecated": false,
              "deprecationReason": null
            }
          ],
          "inputFields": null,
          "interfaces": [

          ],
          "enumValues": null,
          "possibleTypes": null
        },
        {
          "kind": "OBJECT",
          "name": "Mutation",
          "description": null,
          "fields": [
            {
              "name": "CreateComment",
              "description": null,
              "args": [
                {
                  "name": "input",
                  "description": null,
                  "type": {
                    "kind": "NON_NULL",
                    "name": "Non-Null",
                    "ofType": {
                      "kind": "INPUT_OBJECT",
                      "name": "CreateCommentInput",
                      "ofType": null
                    }
                  },
                  "defaultValue": null
                }
              ],
              "type": {
                "kind": "OBJECT",
                "name": "CreateCommentPayload",
                "ofType": null
              },
              "isDeprecated": false,
              "deprecationReason": null
            },
            {
              "name": "CreatePost",
              "description": null,
              "args": [
                {
                  "name": "input",
                  "description": null,
                  "type": {
                    "kind": "NON_NULL",
                    "name": "Non-Null",
                    "ofType": {
                      "kind": "INPUT_OBJECT",
                      "name": "CreatePostInput",
                      "ofType": null
                    }
                  },
                  "defaultValue": null
                }
              ],
              "type": {
                "kind": "OBJECT",
                "name": "CreatePostPayload",
                "ofType": null
              },
              "isDeprecated": false,
              "deprecationReason": null
            },
            {
              "name": "CreateVote",
              "description": null,
              "args": [
                {
                  "name": "input",
                  "description": null,
                  "type": {
                    "kind": "NON_NULL",
                    "name": "Non-Null",
                    "ofType": {
                      "kind": "INPUT_OBJECT",
                      "name": "CreateVoteInput",
                      "ofType": null
                    }
                  },
                  "defaultValue": null
                }
              ],
              "type": {
                "kind": "OBJECT",
                "name": "CreateVotePayload",
                "ofType": null
              },
              "isDeprecated": false,
              "deprecationReason": null
            },
            {
              "name": "DestroyComment",
              "description": null,
              "args": [
                {
                  "name": "input",
                  "description": null,
                  "type": {
                    "kind": "NON_NULL",
                    "name": "Non-Null",
                    "ofType": {
                      "kind": "INPUT_OBJECT",
                      "name": "DestroyCommentInput",
                      "ofType": null
                    }
                  },
                  "defaultValue": null
                }
              ],
              "type": {
                "kind": "OBJECT",
                "name": "DestroyCommentPayload",
                "ofType": null
              },
              "isDeprecated": false,
              "deprecationReason": null
            },
            {
              "name": "DestroyPost",
              "description": null,
              "args": [
                {
                  "name": "input",
                  "description": null,
                  "type": {
                    "kind": "NON_NULL",
                    "name": "Non-Null",
                    "ofType": {
                      "kind": "INPUT_OBJECT",
                      "name": "DestroyPostInput",
                      "ofType": null
                    }
                  },
                  "defaultValue": null
                }
              ],
              "type": {
                "kind": "OBJECT",
                "name": "DestroyPostPayload",
                "ofType": null
              },
              "isDeprecated": false,
              "deprecationReason": null
            },
            {
              "name": "DestroyVote",
              "description": null,
              "args": [
                {
                  "name": "input",
                  "description": null,
                  "type": {
                    "kind": "NON_NULL",
                    "name": "Non-Null",
                    "ofType": {
                      "kind": "INPUT_OBJECT",
                      "name": "DestroyVoteInput",
                      "ofType": null
                    }
                  },
                  "defaultValue": null
                }
              ],
              "type": {
                "kind": "OBJECT",
                "name": "DestroyVotePayload",
                "ofType": null
              },
              "isDeprecated": false,
              "deprecationReason": null
            },
            {
              "name": "EditComment",
              "description": null,
              "args": [
                {
                  "name": "input",
                  "description": null,
                  "type": {
                    "kind": "NON_NULL",
                    "name": "Non-Null",
                    "ofType": {
                      "kind": "INPUT_OBJECT",
                      "name": "EditCommentInput",
                      "ofType": null
                    }
                  },
                  "defaultValue": null
                }
              ],
              "type": {
                "kind": "OBJECT",
                "name": "EditCommentPayload",
                "ofType": null
              },
              "isDeprecated": false,
              "deprecationReason": null
            },
            {
              "name": "EditPost",
              "description": null,
              "args": [
                {
                  "name": "input",
                  "description": null,
                  "type": {
                    "kind": "NON_NULL",
                    "name": "Non-Null",
                    "ofType": {
                      "kind": "INPUT_OBJECT",
                      "name": "EditPostInput",
                      "ofType": null
                    }
                  },
                  "defaultValue": null
                }
              ],
              "type": {
                "kind": "OBJECT",
                "name": "EditPostPayload",
                "ofType": null
              },
              "isDeprecated": false,
              "deprecationReason": null
            }
          ],
          "inputFields": null,
          "interfaces": [

          ],
          "enumValues": null,
          "possibleTypes": null
        },
        {
          "kind": "OBJECT",
          "name": "EditCommentPayload",
          "description": "Autogenerated return type of EditComment",
          "fields": [
            {
              "name": "clientMutationId",
              "description": null,
              "args": [

              ],
              "type": {
                "kind": "NON_NULL",
                "name": "Non-Null",
                "ofType": {
                  "kind": "SCALAR",
                  "name": "String",
                  "ofType": null
                }
              },
              "isDeprecated": false,
              "deprecationReason": null
            },
            {
              "name": "comment",
              "description": null,
              "args": [

              ],
              "type": {
                "kind": "OBJECT",
                "name": "Comment",
                "ofType": null
              },
              "isDeprecated": false,
              "deprecationReason": null
            }
          ],
          "inputFields": null,
          "interfaces": [

          ],
          "enumValues": null,
          "possibleTypes": null
        },
        {
          "kind": "INPUT_OBJECT",
          "name": "EditCommentInput",
          "description": "Autogenerated input type of EditComment",
          "fields": null,
          "inputFields": [
            {
              "name": "clientMutationId",
              "description": null,
              "type": {
                "kind": "NON_NULL",
                "name": "Non-Null",
                "ofType": {
                  "kind": "SCALAR",
                  "name": "String",
                  "ofType": null
                }
              },
              "defaultValue": null
            },
            {
              "name": "id",
              "description": null,
              "type": {
                "kind": "NON_NULL",
                "name": "Non-Null",
                "ofType": {
                  "kind": "SCALAR",
                  "name": "ID",
                  "ofType": null
                }
              },
              "defaultValue": null
            },
            {
              "name": "body",
              "description": null,
              "type": {
                "kind": "NON_NULL",
                "name": "Non-Null",
                "ofType": {
                  "kind": "SCALAR",
                  "name": "String",
                  "ofType": null
                }
              },
              "defaultValue": null
            }
          ],
          "interfaces": null,
          "enumValues": null,
          "possibleTypes": null
        },
        {
          "kind": "OBJECT",
          "name": "DestroyCommentPayload",
          "description": "Autogenerated return type of DestroyComment",
          "fields": [
            {
              "name": "clientMutationId",
              "description": null,
              "args": [

              ],
              "type": {
                "kind": "NON_NULL",
                "name": "Non-Null",
                "ofType": {
                  "kind": "SCALAR",
                  "name": "String",
                  "ofType": null
                }
              },
              "isDeprecated": false,
              "deprecationReason": null
            },
            {
              "name": "deletedId",
              "description": null,
              "args": [

              ],
              "type": {
                "kind": "NON_NULL",
                "name": "Non-Null",
                "ofType": {
                  "kind": "SCALAR",
                  "name": "ID",
                  "ofType": null
                }
              },
              "isDeprecated": false,
              "deprecationReason": null
            },
            {
              "name": "post",
              "description": null,
              "args": [

              ],
              "type": {
                "kind": "OBJECT",
                "name": "Post",
                "ofType": null
              },
              "isDeprecated": false,
              "deprecationReason": null
            }
          ],
          "inputFields": null,
          "interfaces": [

          ],
          "enumValues": null,
          "possibleTypes": null
        },
        {
          "kind": "INPUT_OBJECT",
          "name": "DestroyCommentInput",
          "description": "Autogenerated input type of DestroyComment",
          "fields": null,
          "inputFields": [
            {
              "name": "clientMutationId",
              "description": null,
              "type": {
                "kind": "NON_NULL",
                "name": "Non-Null",
                "ofType": {
                  "kind": "SCALAR",
                  "name": "String",
                  "ofType": null
                }
              },
              "defaultValue": null
            },
            {
              "name": "id",
              "description": null,
              "type": {
                "kind": "NON_NULL",
                "name": "Non-Null",
                "ofType": {
                  "kind": "SCALAR",
                  "name": "ID",
                  "ofType": null
                }
              },
              "defaultValue": null
            },
            {
              "name": "post_id",
              "description": null,
              "type": {
                "kind": "NON_NULL",
                "name": "Non-Null",
                "ofType": {
                  "kind": "SCALAR",
                  "name": "ID",
                  "ofType": null
                }
              },
              "defaultValue": null
            }
          ],
          "interfaces": null,
          "enumValues": null,
          "possibleTypes": null
        },
        {
          "kind": "OBJECT",
          "name": "CreateCommentPayload",
          "description": "Autogenerated return type of CreateComment",
          "fields": [
            {
              "name": "clientMutationId",
              "description": null,
              "args": [

              ],
              "type": {
                "kind": "NON_NULL",
                "name": "Non-Null",
                "ofType": {
                  "kind": "SCALAR",
                  "name": "String",
                  "ofType": null
                }
              },
              "isDeprecated": false,
              "deprecationReason": null
            },
            {
              "name": "commentEdge",
              "description": null,
              "args": [

              ],
              "type": {
                "kind": "OBJECT",
                "name": "CommentEdge",
                "ofType": null
              },
              "isDeprecated": false,
              "deprecationReason": null
            },
            {
              "name": "post",
              "description": null,
              "args": [

              ],
              "type": {
                "kind": "OBJECT",
                "name": "Post",
                "ofType": null
              },
              "isDeprecated": false,
              "deprecationReason": null
            }
          ],
          "inputFields": null,
          "interfaces": [

          ],
          "enumValues": null,
          "possibleTypes": null
        },
        {
          "kind": "INPUT_OBJECT",
          "name": "CreateCommentInput",
          "description": "Autogenerated input type of CreateComment",
          "fields": null,
          "inputFields": [
            {
              "name": "clientMutationId",
              "description": null,
              "type": {
                "kind": "NON_NULL",
                "name": "Non-Null",
                "ofType": {
                  "kind": "SCALAR",
                  "name": "String",
                  "ofType": null
                }
              },
              "defaultValue": null
            },
            {
              "name": "post_id",
              "description": null,
              "type": {
                "kind": "NON_NULL",
                "name": "Non-Null",
                "ofType": {
                  "kind": "SCALAR",
                  "name": "ID",
                  "ofType": null
                }
              },
              "defaultValue": null
            },
            {
              "name": "body",
              "description": null,
              "type": {
                "kind": "NON_NULL",
                "name": "Non-Null",
                "ofType": {
                  "kind": "SCALAR",
                  "name": "String",
                  "ofType": null
                }
              },
              "defaultValue": null
            }
          ],
          "interfaces": null,
          "enumValues": null,
          "possibleTypes": null
        },
        {
          "kind": "OBJECT",
          "name": "DestroyVotePayload",
          "description": "Autogenerated return type of DestroyVote",
          "fields": [
            {
              "name": "clientMutationId",
              "description": null,
              "args": [

              ],
              "type": {
                "kind": "NON_NULL",
                "name": "Non-Null",
                "ofType": {
                  "kind": "SCALAR",
                  "name": "String",
                  "ofType": null
                }
              },
              "isDeprecated": false,
              "deprecationReason": null
            },
            {
              "name": "comment",
              "description": null,
              "args": [

              ],
              "type": {
                "kind": "OBJECT",
                "name": "Comment",
                "ofType": null
              },
              "isDeprecated": false,
              "deprecationReason": null
            },
            {
              "name": "post",
              "description": null,
              "args": [

              ],
              "type": {
                "kind": "OBJECT",
                "name": "Post",
                "ofType": null
              },
              "isDeprecated": false,
              "deprecationReason": null
            }
          ],
          "inputFields": null,
          "interfaces": [

          ],
          "enumValues": null,
          "possibleTypes": null
        },
        {
          "kind": "INPUT_OBJECT",
          "name": "DestroyVoteInput",
          "description": "Autogenerated input type of DestroyVote",
          "fields": null,
          "inputFields": [
            {
              "name": "clientMutationId",
              "description": null,
              "type": {
                "kind": "NON_NULL",
                "name": "Non-Null",
                "ofType": {
                  "kind": "SCALAR",
                  "name": "String",
                  "ofType": null
                }
              },
              "defaultValue": null
            },
            {
              "name": "votable_id",
              "description": null,
              "type": {
                "kind": "NON_NULL",
                "name": "Non-Null",
                "ofType": {
                  "kind": "SCALAR",
                  "name": "ID",
                  "ofType": null
                }
              },
              "defaultValue": null
            }
          ],
          "interfaces": null,
          "enumValues": null,
          "possibleTypes": null
        },
        {
          "kind": "OBJECT",
          "name": "CreateVotePayload",
          "description": "Autogenerated return type of CreateVote",
          "fields": [
            {
              "name": "clientMutationId",
              "description": null,
              "args": [

              ],
              "type": {
                "kind": "NON_NULL",
                "name": "Non-Null",
                "ofType": {
                  "kind": "SCALAR",
                  "name": "String",
                  "ofType": null
                }
              },
              "isDeprecated": false,
              "deprecationReason": null
            },
            {
              "name": "comment",
              "description": null,
              "args": [

              ],
              "type": {
                "kind": "OBJECT",
                "name": "Comment",
                "ofType": null
              },
              "isDeprecated": false,
              "deprecationReason": null
            },
            {
              "name": "post",
              "description": null,
              "args": [

              ],
              "type": {
                "kind": "OBJECT",
                "name": "Post",
                "ofType": null
              },
              "isDeprecated": false,
              "deprecationReason": null
            }
          ],
          "inputFields": null,
          "interfaces": [

          ],
          "enumValues": null,
          "possibleTypes": null
        },
        {
          "kind": "INPUT_OBJECT",
          "name": "CreateVoteInput",
          "description": "Autogenerated input type of CreateVote",
          "fields": null,
          "inputFields": [
            {
              "name": "clientMutationId",
              "description": null,
              "type": {
                "kind": "NON_NULL",
                "name": "Non-Null",
                "ofType": {
                  "kind": "SCALAR",
                  "name": "String",
                  "ofType": null
                }
              },
              "defaultValue": null
            },
            {
              "name": "votable_id",
              "description": null,
              "type": {
                "kind": "NON_NULL",
                "name": "Non-Null",
                "ofType": {
                  "kind": "SCALAR",
                  "name": "ID",
                  "ofType": null
                }
              },
              "defaultValue": null
            }
          ],
          "interfaces": null,
          "enumValues": null,
          "possibleTypes": null
        },
        {
          "kind": "OBJECT",
          "name": "DestroyPostPayload",
          "description": "Autogenerated return type of DestroyPost",
          "fields": [
            {
              "name": "clientMutationId",
              "description": null,
              "args": [

              ],
              "type": {
                "kind": "NON_NULL",
                "name": "Non-Null",
                "ofType": {
                  "kind": "SCALAR",
                  "name": "String",
                  "ofType": null
                }
              },
              "isDeprecated": false,
              "deprecationReason": null
            },
            {
              "name": "deletedId",
              "description": null,
              "args": [

              ],
              "type": {
                "kind": "NON_NULL",
                "name": "Non-Null",
                "ofType": {
                  "kind": "SCALAR",
                  "name": "ID",
                  "ofType": null
                }
              },
              "isDeprecated": false,
              "deprecationReason": null
            },
            {
              "name": "viewer",
              "description": null,
              "args": [

              ],
              "type": {
                "kind": "OBJECT",
                "name": "Viewer",
                "ofType": null
              },
              "isDeprecated": false,
              "deprecationReason": null
            }
          ],
          "inputFields": null,
          "interfaces": [

          ],
          "enumValues": null,
          "possibleTypes": null
        },
        {
          "kind": "INPUT_OBJECT",
          "name": "DestroyPostInput",
          "description": "Autogenerated input type of DestroyPost",
          "fields": null,
          "inputFields": [
            {
              "name": "clientMutationId",
              "description": null,
              "type": {
                "kind": "NON_NULL",
                "name": "Non-Null",
                "ofType": {
                  "kind": "SCALAR",
                  "name": "String",
                  "ofType": null
                }
              },
              "defaultValue": null
            },
            {
              "name": "id",
              "description": null,
              "type": {
                "kind": "NON_NULL",
                "name": "Non-Null",
                "ofType": {
                  "kind": "SCALAR",
                  "name": "ID",
                  "ofType": null
                }
              },
              "defaultValue": null
            }
          ],
          "interfaces": null,
          "enumValues": null,
          "possibleTypes": null
        },
        {
          "kind": "OBJECT",
          "name": "CreatePostPayload",
          "description": "Autogenerated return type of CreatePost",
          "fields": [
            {
              "name": "clientMutationId",
              "description": null,
              "args": [

              ],
              "type": {
                "kind": "NON_NULL",
                "name": "Non-Null",
                "ofType": {
                  "kind": "SCALAR",
                  "name": "String",
                  "ofType": null
                }
              },
              "isDeprecated": false,
              "deprecationReason": null
            },
            {
              "name": "postEdge",
              "description": null,
              "args": [

              ],
              "type": {
                "kind": "OBJECT",
                "name": "PostEdge",
                "ofType": null
              },
              "isDeprecated": false,
              "deprecationReason": null
            },
            {
              "name": "viewer",
              "description": null,
              "args": [

              ],
              "type": {
                "kind": "OBJECT",
                "name": "Viewer",
                "ofType": null
              },
              "isDeprecated": false,
              "deprecationReason": null
            }
          ],
          "inputFields": null,
          "interfaces": [

          ],
          "enumValues": null,
          "possibleTypes": null
        },
        {
          "kind": "INPUT_OBJECT",
          "name": "CreatePostInput",
          "description": "Autogenerated input type of CreatePost",
          "fields": null,
          "inputFields": [
            {
              "name": "clientMutationId",
              "description": null,
              "type": {
                "kind": "NON_NULL",
                "name": "Non-Null",
                "ofType": {
                  "kind": "SCALAR",
                  "name": "String",
                  "ofType": null
                }
              },
              "defaultValue": null
            },
            {
              "name": "title",
              "description": null,
              "type": {
                "kind": "NON_NULL",
                "name": "Non-Null",
                "ofType": {
                  "kind": "SCALAR",
                  "name": "String",
                  "ofType": null
                }
              },
              "defaultValue": null
            },
            {
              "name": "excerpt",
              "description": null,
              "type": {
                "kind": "NON_NULL",
                "name": "Non-Null",
                "ofType": {
                  "kind": "SCALAR",
                  "name": "String",
                  "ofType": null
                }
              },
              "defaultValue": null
            },
            {
              "name": "body",
              "description": null,
              "type": {
                "kind": "NON_NULL",
                "name": "Non-Null",
                "ofType": {
                  "kind": "SCALAR",
                  "name": "String",
                  "ofType": null
                }
              },
              "defaultValue": null
            },
            {
              "name": "viewer_id",
              "description": null,
              "type": {
                "kind": "NON_NULL",
                "name": "Non-Null",
                "ofType": {
                  "kind": "SCALAR",
                  "name": "ID",
                  "ofType": null
                }
              },
              "defaultValue": null
            }
          ],
          "interfaces": null,
          "enumValues": null,
          "possibleTypes": null
        },
        {
          "kind": "OBJECT",
          "name": "EditPostPayload",
          "description": "Autogenerated return type of EditPost",
          "fields": [
            {
              "name": "clientMutationId",
              "description": null,
              "args": [

              ],
              "type": {
                "kind": "NON_NULL",
                "name": "Non-Null",
                "ofType": {
                  "kind": "SCALAR",
                  "name": "String",
                  "ofType": null
                }
              },
              "isDeprecated": false,
              "deprecationReason": null
            },
            {
              "name": "post",
              "description": null,
              "args": [

              ],
              "type": {
                "kind": "OBJECT",
                "name": "Post",
                "ofType": null
              },
              "isDeprecated": false,
              "deprecationReason": null
            }
          ],
          "inputFields": null,
          "interfaces": [

          ],
          "enumValues": null,
          "possibleTypes": null
        },
        {
          "kind": "INPUT_OBJECT",
          "name": "EditPostInput",
          "description": "Autogenerated input type of EditPost",
          "fields": null,
          "inputFields": [
            {
              "name": "clientMutationId",
              "description": null,
              "type": {
                "kind": "NON_NULL",
                "name": "Non-Null",
                "ofType": {
                  "kind": "SCALAR",
                  "name": "String",
                  "ofType": null
                }
              },
              "defaultValue": null
            },
            {
              "name": "id",
              "description": null,
              "type": {
                "kind": "NON_NULL",
                "name": "Non-Null",
                "ofType": {
                  "kind": "SCALAR",
                  "name": "ID",
                  "ofType": null
                }
              },
              "defaultValue": null
            }
          ],
          "interfaces": null,
          "enumValues": null,
          "possibleTypes": null
        },
        {
          "kind": "OBJECT",
          "name": "__Schema",
          "description": "A GraphQL schema",
          "fields": [
            {
              "name": "directives",
              "description": "Directives in this schema",
              "args": [

              ],
              "type": {
                "kind": "NON_NULL",
                "name": "Non-Null",
                "ofType": {
                  "kind": "LIST",
                  "name": "List",
                  "ofType": {
                    "kind": "NON_NULL",
                    "name": "Non-Null",
                    "ofType": {
                      "kind": "OBJECT",
                      "name": "__Directive"
                    }
                  }
                }
              },
              "isDeprecated": false,
              "deprecationReason": null
            },
            {
              "name": "mutationType",
              "description": "The mutation root of this schema",
              "args": [

              ],
              "type": {
                "kind": "OBJECT",
                "name": "__Type",
                "ofType": null
              },
              "isDeprecated": false,
              "deprecationReason": null
            },
            {
              "name": "queryType",
              "description": "The query root of this schema",
              "args": [

              ],
              "type": {
                "kind": "NON_NULL",
                "name": "Non-Null",
                "ofType": {
                  "kind": "OBJECT",
                  "name": "__Type",
                  "ofType": null
                }
              },
              "isDeprecated": false,
              "deprecationReason": null
            },
            {
              "name": "subscriptionType",
              "description": "The subscription root of this schema",
              "args": [

              ],
              "type": {
                "kind": "OBJECT",
                "name": "__Type",
                "ofType": null
              },
              "isDeprecated": false,
              "deprecationReason": null
            },
            {
              "name": "types",
              "description": "Types in this schema",
              "args": [

              ],
              "type": {
                "kind": "NON_NULL",
                "name": "Non-Null",
                "ofType": {
                  "kind": "LIST",
                  "name": "List",
                  "ofType": {
                    "kind": "NON_NULL",
                    "name": "Non-Null",
                    "ofType": {
                      "kind": "OBJECT",
                      "name": "__Type"
                    }
                  }
                }
              },
              "isDeprecated": false,
              "deprecationReason": null
            }
          ],
          "inputFields": null,
          "interfaces": [

          ],
          "enumValues": null,
          "possibleTypes": null
        },
        {
          "kind": "OBJECT",
          "name": "__Type",
          "description": "A type in the GraphQL schema",
          "fields": [
            {
              "name": "description",
              "description": "What this type represents",
              "args": [

              ],
              "type": {
                "kind": "SCALAR",
                "name": "String",
                "ofType": null
              },
              "isDeprecated": false,
              "deprecationReason": null
            },
            {
              "name": "enumValues",
              "description": "Values for this enum",
              "args": [
                {
                  "name": "includeDeprecated",
                  "description": null,
                  "type": {
                    "kind": "SCALAR",
                    "name": "Boolean",
                    "ofType": null
                  },
                  "defaultValue": "false"
                }
              ],
              "type": {
                "kind": "LIST",
                "name": "List",
                "ofType": {
                  "kind": "NON_NULL",
                  "name": "Non-Null",
                  "ofType": {
                    "kind": "OBJECT",
                    "name": "__EnumValue",
                    "ofType": null
                  }
                }
              },
              "isDeprecated": false,
              "deprecationReason": null
            },
            {
              "name": "fields",
              "description": "List of fields on this object",
              "args": [
                {
                  "name": "includeDeprecated",
                  "description": null,
                  "type": {
                    "kind": "SCALAR",
                    "name": "Boolean",
                    "ofType": null
                  },
                  "defaultValue": "false"
                }
              ],
              "type": {
                "kind": "LIST",
                "name": "List",
                "ofType": {
                  "kind": "NON_NULL",
                  "name": "Non-Null",
                  "ofType": {
                    "kind": "OBJECT",
                    "name": "__Field",
                    "ofType": null
                  }
                }
              },
              "isDeprecated": false,
              "deprecationReason": null
            },
            {
              "name": "inputFields",
              "description": "fields on this input object",
              "args": [

              ],
              "type": {
                "kind": "LIST",
                "name": "List",
                "ofType": {
                  "kind": "NON_NULL",
                  "name": "Non-Null",
                  "ofType": {
                    "kind": "OBJECT",
                    "name": "__InputValue",
                    "ofType": null
                  }
                }
              },
              "isDeprecated": false,
              "deprecationReason": null
            },
            {
              "name": "interfaces",
              "description": "Interfaces which this object implements",
              "args": [

              ],
              "type": {
                "kind": "LIST",
                "name": "List",
                "ofType": {
                  "kind": "NON_NULL",
                  "name": "Non-Null",
                  "ofType": {
                    "kind": "OBJECT",
                    "name": "__Type",
                    "ofType": null
                  }
                }
              },
              "isDeprecated": false,
              "deprecationReason": null
            },
            {
              "name": "kind",
              "description": "The kind of this type",
              "args": [

              ],
              "type": {
                "kind": "NON_NULL",
                "name": "Non-Null",
                "ofType": {
                  "kind": "ENUM",
                  "name": "__TypeKind",
                  "ofType": null
                }
              },
              "isDeprecated": false,
              "deprecationReason": null
            },
            {
              "name": "name",
              "description": "The name of this type",
              "args": [

              ],
              "type": {
                "kind": "SCALAR",
                "name": "String",
                "ofType": null
              },
              "isDeprecated": false,
              "deprecationReason": null
            },
            {
              "name": "ofType",
              "description": "The modified type of this type",
              "args": [

              ],
              "type": {
                "kind": "OBJECT",
                "name": "__Type",
                "ofType": null
              },
              "isDeprecated": false,
              "deprecationReason": null
            },
            {
              "name": "possibleTypes",
              "description": "Types which compose this Union or Interface",
              "args": [

              ],
              "type": {
                "kind": "LIST",
                "name": "List",
                "ofType": {
                  "kind": "NON_NULL",
                  "name": "Non-Null",
                  "ofType": {
                    "kind": "OBJECT",
                    "name": "__Type",
                    "ofType": null
                  }
                }
              },
              "isDeprecated": false,
              "deprecationReason": null
            }
          ],
          "inputFields": null,
          "interfaces": [

          ],
          "enumValues": null,
          "possibleTypes": null
        },
        {
          "kind": "ENUM",
          "name": "__TypeKind",
          "description": "The kinds of types in this GraphQL system",
          "fields": null,
          "inputFields": null,
          "interfaces": null,
          "enumValues": [
            {
              "name": "SCALAR",
              "description": null,
              "isDeprecated": false,
              "deprecationReason": null
            },
            {
              "name": "OBJECT",
              "description": null,
              "isDeprecated": false,
              "deprecationReason": null
            },
            {
              "name": "INTERFACE",
              "description": null,
              "isDeprecated": false,
              "deprecationReason": null
            },
            {
              "name": "UNION",
              "description": null,
              "isDeprecated": false,
              "deprecationReason": null
            },
            {
              "name": "ENUM",
              "description": null,
              "isDeprecated": false,
              "deprecationReason": null
            },
            {
              "name": "INPUT_OBJECT",
              "description": null,
              "isDeprecated": false,
              "deprecationReason": null
            },
            {
              "name": "LIST",
              "description": null,
              "isDeprecated": false,
              "deprecationReason": null
            },
            {
              "name": "NON_NULL",
              "description": null,
              "isDeprecated": false,
              "deprecationReason": null
            }
          ],
          "possibleTypes": null
        },
        {
          "kind": "OBJECT",
          "name": "__Field",
          "description": "Field on a GraphQL type",
          "fields": [
            {
              "name": "args",
              "description": "Arguments allowed to this object",
              "args": [

              ],
              "type": {
                "kind": "NON_NULL",
                "name": "Non-Null",
                "ofType": {
                  "kind": "LIST",
                  "name": "List",
                  "ofType": {
                    "kind": "NON_NULL",
                    "name": "Non-Null",
                    "ofType": {
                      "kind": "OBJECT",
                      "name": "__InputValue"
                    }
                  }
                }
              },
              "isDeprecated": false,
              "deprecationReason": null
            },
            {
              "name": "deprecationReason",
              "description": "Why this field was deprecated",
              "args": [

              ],
              "type": {
                "kind": "SCALAR",
                "name": "String",
                "ofType": null
              },
              "isDeprecated": false,
              "deprecationReason": null
            },
            {
              "name": "description",
              "description": "The description of this field",
              "args": [

              ],
              "type": {
                "kind": "SCALAR",
                "name": "String",
                "ofType": null
              },
              "isDeprecated": false,
              "deprecationReason": null
            },
            {
              "name": "isDeprecated",
              "description": "Is this field deprecated?",
              "args": [

              ],
              "type": {
                "kind": "NON_NULL",
                "name": "Non-Null",
                "ofType": {
                  "kind": "SCALAR",
                  "name": "Boolean",
                  "ofType": null
                }
              },
              "isDeprecated": false,
              "deprecationReason": null
            },
            {
              "name": "name",
              "description": "The name for accessing this field",
              "args": [

              ],
              "type": {
                "kind": "NON_NULL",
                "name": "Non-Null",
                "ofType": {
                  "kind": "SCALAR",
                  "name": "String",
                  "ofType": null
                }
              },
              "isDeprecated": false,
              "deprecationReason": null
            },
            {
              "name": "type",
              "description": "The return type of this field",
              "args": [

              ],
              "type": {
                "kind": "NON_NULL",
                "name": "Non-Null",
                "ofType": {
                  "kind": "OBJECT",
                  "name": "__Type",
                  "ofType": null
                }
              },
              "isDeprecated": false,
              "deprecationReason": null
            }
          ],
          "inputFields": null,
          "interfaces": [

          ],
          "enumValues": null,
          "possibleTypes": null
        },
        {
          "kind": "OBJECT",
          "name": "__InputValue",
          "description": "An input for a field or InputObject",
          "fields": [
            {
              "name": "defaultValue",
              "description": "The value applied if no other value is provided",
              "args": [

              ],
              "type": {
                "kind": "SCALAR",
                "name": "String",
                "ofType": null
              },
              "isDeprecated": false,
              "deprecationReason": null
            },
            {
              "name": "description",
              "description": "What this value is used for",
              "args": [

              ],
              "type": {
                "kind": "SCALAR",
                "name": "String",
                "ofType": null
              },
              "isDeprecated": false,
              "deprecationReason": null
            },
            {
              "name": "name",
              "description": "The key for this value",
              "args": [

              ],
              "type": {
                "kind": "NON_NULL",
                "name": "Non-Null",
                "ofType": {
                  "kind": "SCALAR",
                  "name": "String",
                  "ofType": null
                }
              },
              "isDeprecated": false,
              "deprecationReason": null
            },
            {
              "name": "type",
              "description": "The expected type for this value",
              "args": [

              ],
              "type": {
                "kind": "NON_NULL",
                "name": "Non-Null",
                "ofType": {
                  "kind": "OBJECT",
                  "name": "__Type",
                  "ofType": null
                }
              },
              "isDeprecated": false,
              "deprecationReason": null
            }
          ],
          "inputFields": null,
          "interfaces": [

          ],
          "enumValues": null,
          "possibleTypes": null
        },
        {
          "kind": "OBJECT",
          "name": "__EnumValue",
          "description": "A possible value for an Enum",
          "fields": [
            {
              "name": "deprecationReason",
              "description": null,
              "args": [

              ],
              "type": {
                "kind": "SCALAR",
                "name": "String",
                "ofType": null
              },
              "isDeprecated": false,
              "deprecationReason": null
            },
            {
              "name": "description",
              "description": null,
              "args": [

              ],
              "type": {
                "kind": "SCALAR",
                "name": "String",
                "ofType": null
              },
              "isDeprecated": false,
              "deprecationReason": null
            },
            {
              "name": "isDeprecated",
              "description": null,
              "args": [

              ],
              "type": {
                "kind": "NON_NULL",
                "name": "Non-Null",
                "ofType": {
                  "kind": "SCALAR",
                  "name": "Boolean",
                  "ofType": null
                }
              },
              "isDeprecated": false,
              "deprecationReason": null
            },
            {
              "name": "name",
              "description": null,
              "args": [

              ],
              "type": {
                "kind": "NON_NULL",
                "name": "Non-Null",
                "ofType": {
                  "kind": "SCALAR",
                  "name": "String",
                  "ofType": null
                }
              },
              "isDeprecated": false,
              "deprecationReason": null
            }
          ],
          "inputFields": null,
          "interfaces": [

          ],
          "enumValues": null,
          "possibleTypes": null
        },
        {
          "kind": "OBJECT",
          "name": "__Directive",
          "description": "A query directive in this schema",
          "fields": [
            {
              "name": "args",
              "description": "Arguments allowed to this object",
              "args": [

              ],
              "type": {
                "kind": "NON_NULL",
                "name": "Non-Null",
                "ofType": {
                  "kind": "LIST",
                  "name": "List",
                  "ofType": {
                    "kind": "NON_NULL",
                    "name": "Non-Null",
                    "ofType": {
                      "kind": "OBJECT",
                      "name": "__InputValue"
                    }
                  }
                }
              },
              "isDeprecated": false,
              "deprecationReason": null
            },
            {
              "name": "description",
              "description": "The description for this type",
              "args": [

              ],
              "type": {
                "kind": "SCALAR",
                "name": "String",
                "ofType": null
              },
              "isDeprecated": false,
              "deprecationReason": null
            },
            {
              "name": "locations",
              "description": null,
              "args": [

              ],
              "type": {
                "kind": "NON_NULL",
                "name": "Non-Null",
                "ofType": {
                  "kind": "LIST",
                  "name": "List",
                  "ofType": {
                    "kind": "NON_NULL",
                    "name": "Non-Null",
                    "ofType": {
                      "kind": "ENUM",
                      "name": "__DirectiveLocation"
                    }
                  }
                }
              },
              "isDeprecated": false,
              "deprecationReason": null
            },
            {
              "name": "name",
              "description": "The name of this directive",
              "args": [

              ],
              "type": {
                "kind": "NON_NULL",
                "name": "Non-Null",
                "ofType": {
                  "kind": "SCALAR",
                  "name": "String",
                  "ofType": null
                }
              },
              "isDeprecated": false,
              "deprecationReason": null
            }
          ],
          "inputFields": null,
          "interfaces": [

          ],
          "enumValues": null,
          "possibleTypes": null
        },
        {
          "kind": "ENUM",
          "name": "__DirectiveLocation",
          "description": "Parts of the query where a directive may be located",
          "fields": null,
          "inputFields": null,
          "interfaces": null,
          "enumValues": [
            {
              "name": "QUERY",
              "description": null,
              "isDeprecated": false,
              "deprecationReason": null
            },
            {
              "name": "MUTATION",
              "description": null,
              "isDeprecated": false,
              "deprecationReason": null
            },
            {
              "name": "SUBSCRIPTION",
              "description": null,
              "isDeprecated": false,
              "deprecationReason": null
            },
            {
              "name": "FIELD",
              "description": null,
              "isDeprecated": false,
              "deprecationReason": null
            },
            {
              "name": "FRAGMENT_DEFINITION",
              "description": null,
              "isDeprecated": false,
              "deprecationReason": null
            },
            {
              "name": "FRAGMENT_SPREAD",
              "description": null,
              "isDeprecated": false,
              "deprecationReason": null
            },
            {
              "name": "INLINE_FRAGMENT",
              "description": null,
              "isDeprecated": false,
              "deprecationReason": null
            }
          ],
          "possibleTypes": null
        }
      ],
      "directives": [
        {
          "name": "skip",
          "description": "Ignore this part of the query if `if` is true",
          "locations": [
            "FIELD",
            "FRAGMENT_SPREAD",
            "INLINE_FRAGMENT"
          ],
          "args": [
            {
              "name": "if",
              "description": null,
              "type": {
                "kind": "NON_NULL",
                "name": "Non-Null",
                "ofType": {
                  "kind": "SCALAR",
                  "name": "Boolean",
                  "ofType": null
                }
              },
              "defaultValue": null
            }
          ]
        },
        {
          "name": "include",
          "description": "Include this part of the query if `if` is true",
          "locations": [
            "FIELD",
            "FRAGMENT_SPREAD",
            "INLINE_FRAGMENT"
          ],
          "args": [
            {
              "name": "if",
              "description": null,
              "type": {
                "kind": "NON_NULL",
                "name": "Non-Null",
                "ofType": {
                  "kind": "SCALAR",
                  "name": "Boolean",
                  "ofType": null
                }
              },
              "defaultValue": null
            }
          ]
        }
      ]
    }
  }
}